<?xml version="1.0" encoding="UTF-8"?>
<!DOCTYPE mapper PUBLIC "-//mybatis.org//DTD Mapper 3.0//EN" "http://mybatis.org/dtd/mybatis-3-mapper.dtd">
<mapper namespace="cn.lz.szp.dao.CourseDao">
  <resultMap id="BaseResultMap" type="cn.lz.szp.pojo.entity.Course">
    <id column="course_id" jdbcType="BIGINT" property="courseId" />
    <result column="title" jdbcType="VARCHAR" property="title" />
    <result column="subtitle" jdbcType="VARCHAR" property="subtitle" />
    <result column="teacher_id" jdbcType="BIGINT" property="teacherId" />
    <result column="release_time" jdbcType="TIMESTAMP" property="releaseTime" />
    <result column="version" jdbcType="VARCHAR" property="version" />
    <result column="origin_price" jdbcType="DECIMAL" property="originPrice" />
    <result column="now_price" jdbcType="DECIMAL" property="nowPrice" />
    <result column="img" jdbcType="VARCHAR" property="img" />
    <result column="detail" jdbcType="VARCHAR" property="detail" />
    <result column="sort" jdbcType="INTEGER" property="sort" />
    <result column="watch_count" jdbcType="INTEGER" property="watchCount" />
    <result column="on_sale" jdbcType="BOOLEAN" property="onSale" />
    <result column="type_id" jdbcType="INTEGER" property="typeId" />
    <result column="bought_users" jdbcType="VARCHAR" property="boughtUsers" />
    <result column="bought_count" jdbcType="INTEGER" property="boughtCount" />
    <result column="create_time" jdbcType="TIMESTAMP" property="createTime" />
    <result column="update_time" jdbcType="TIMESTAMP" property="updateTime" />
  </resultMap>
  <sql id="Base_Column_List">
    course_id, title, subtitle, teacher_id, release_time, version, origin_price, now_price, 
    img, detail, sort, watch_count, on_sale, type_id, bought_users, bought_count, create_time, 
    update_time
  </sql>
  <select id="selectByPrimaryKey" parameterType="java.lang.Long" resultMap="BaseResultMap">
    select 
    <include refid="Base_Column_List" />
    from course
    where course_id = #{courseId,jdbcType=BIGINT}
  </select>
  <delete id="deleteByPrimaryKey" parameterType="java.lang.Long">
    delete from course
    where course_id = #{courseId,jdbcType=BIGINT}
  </delete>
  <insert id="insert" keyColumn="course_id" keyProperty="courseId" parameterType="cn.lz.szp.pojo.entity.Course" useGeneratedKeys="true">
    insert into course (title, subtitle, teacher_id, 
      release_time, version, origin_price, 
      now_price, img, detail, 
      sort, watch_count, on_sale, 
      type_id, bought_users, bought_count, 
      create_time, update_time)
    values (#{title,jdbcType=VARCHAR}, #{subtitle,jdbcType=VARCHAR}, #{teacherId,jdbcType=BIGINT}, 
      #{releaseTime,jdbcType=TIMESTAMP}, #{version,jdbcType=VARCHAR}, #{originPrice,jdbcType=DECIMAL}, 
      #{nowPrice,jdbcType=DECIMAL}, #{img,jdbcType=VARCHAR}, #{detail,jdbcType=VARCHAR}, 
      #{sort,jdbcType=INTEGER}, #{watchCount,jdbcType=INTEGER}, #{onSale,jdbcType=BOOLEAN}, 
      #{typeId,jdbcType=INTEGER}, #{boughtUsers,jdbcType=VARCHAR}, #{boughtCount,jdbcType=INTEGER}, 
      #{createTime,jdbcType=TIMESTAMP}, #{updateTime,jdbcType=TIMESTAMP})
  </insert>
  <insert id="insertSelective" keyColumn="course_id" keyProperty="courseId" parameterType="cn.lz.szp.pojo.entity.Course" useGeneratedKeys="true">
    insert into course
    <trim prefix="(" suffix=")" suffixOverrides=",">
      <if test="title != null">
        title,
      </if>
      <if test="subtitle != null">
        subtitle,
      </if>
      <if test="teacherId != null">
        teacher_id,
      </if>
      <if test="releaseTime != null">
        release_time,
      </if>
      <if test="version != null">
        version,
      </if>
      <if test="originPrice != null">
        origin_price,
      </if>
      <if test="nowPrice != null">
        now_price,
      </if>
      <if test="img != null">
        img,
      </if>
      <if test="detail != null">
        detail,
      </if>
      <if test="sort != null">
        sort,
      </if>
      <if test="watchCount != null">
        watch_count,
      </if>
      <if test="onSale != null">
        on_sale,
      </if>
      <if test="typeId != null">
        type_id,
      </if>
      <if test="boughtUsers != null">
        bought_users,
      </if>
      <if test="boughtCount != null">
        bought_count,
      </if>
      <if test="createTime != null">
        create_time,
      </if>
      <if test="updateTime != null">
        update_time,
      </if>
    </trim>
    <trim prefix="values (" suffix=")" suffixOverrides=",">
      <if test="title != null">
        #{title,jdbcType=VARCHAR},
      </if>
      <if test="subtitle != null">
        #{subtitle,jdbcType=VARCHAR},
      </if>
      <if test="teacherId != null">
        #{teacherId,jdbcType=BIGINT},
      </if>
      <if test="releaseTime != null">
        #{releaseTime,jdbcType=TIMESTAMP},
      </if>
      <if test="version != null">
        #{version,jdbcType=VARCHAR},
      </if>
      <if test="originPrice != null">
        #{originPrice,jdbcType=DECIMAL},
      </if>
      <if test="nowPrice != null">
        #{nowPrice,jdbcType=DECIMAL},
      </if>
      <if test="img != null">
        #{img,jdbcType=VARCHAR},
      </if>
      <if test="detail != null">
        #{detail,jdbcType=VARCHAR},
      </if>
      <if test="sort != null">
        #{sort,jdbcType=INTEGER},
      </if>
      <if test="watchCount != null">
        #{watchCount,jdbcType=INTEGER},
      </if>
      <if test="onSale != null">
        #{onSale,jdbcType=BOOLEAN},
      </if>
      <if test="typeId != null">
        #{typeId,jdbcType=INTEGER},
      </if>
      <if test="boughtUsers != null">
        #{boughtUsers,jdbcType=VARCHAR},
      </if>
      <if test="boughtCount != null">
        #{boughtCount,jdbcType=INTEGER},
      </if>
      <if test="createTime != null">
        #{createTime,jdbcType=TIMESTAMP},
      </if>
      <if test="updateTime != null">
        #{updateTime,jdbcType=TIMESTAMP},
      </if>
    </trim>
  </insert>
  <update id="updateByPrimaryKeySelective" parameterType="cn.lz.szp.pojo.entity.Course">
    update course
    <set>
      <if test="title != null">
        title = #{title,jdbcType=VARCHAR},
      </if>
      <if test="subtitle != null">
        subtitle = #{subtitle,jdbcType=VARCHAR},
      </if>
      <if test="teacherId != null">
        teacher_id = #{teacherId,jdbcType=BIGINT},
      </if>
      <if test="releaseTime != null">
        release_time = #{releaseTime,jdbcType=TIMESTAMP},
      </if>
      <if test="version != null">
        version = #{version,jdbcType=VARCHAR},
      </if>
      <if test="originPrice != null">
        origin_price = #{originPrice,jdbcType=DECIMAL},
      </if>
      <if test="nowPrice != null">
        now_price = #{nowPrice,jdbcType=DECIMAL},
      </if>
      <if test="img != null">
        img = #{img,jdbcType=VARCHAR},
      </if>
      <if test="detail != null">
        detail = #{detail,jdbcType=VARCHAR},
      </if>
      <if test="sort != null">
        sort = #{sort,jdbcType=INTEGER},
      </if>
      <if test="watchCount != null">
        watch_count = #{watchCount,jdbcType=INTEGER},
      </if>
      <if test="onSale != null">
        on_sale = #{onSale,jdbcType=BOOLEAN},
      </if>
      <if test="typeId != null">
        type_id = #{typeId,jdbcType=INTEGER},
      </if>
      <if test="boughtUsers != null">
        bought_users = #{boughtUsers,jdbcType=VARCHAR},
      </if>
      <if test="boughtCount != null">
        bought_count = #{boughtCount,jdbcType=INTEGER},
      </if>
      <if test="createTime != null">
        create_time = #{createTime,jdbcType=TIMESTAMP},
      </if>
      <if test="updateTime != null">
        update_time = #{updateTime,jdbcType=TIMESTAMP},
      </if>
    </set>
    where course_id = #{courseId,jdbcType=BIGINT}
  </update>
  <update id="updateByPrimaryKey" parameterType="cn.lz.szp.pojo.entity.Course">
    update course
    set title = #{title,jdbcType=VARCHAR},
      subtitle = #{subtitle,jdbcType=VARCHAR},
      teacher_id = #{teacherId,jdbcType=BIGINT},
      release_time = #{releaseTime,jdbcType=TIMESTAMP},
      version = #{version,jdbcType=VARCHAR},
      origin_price = #{originPrice,jdbcType=DECIMAL},
      now_price = #{nowPrice,jdbcType=DECIMAL},
      img = #{img,jdbcType=VARCHAR},
      detail = #{detail,jdbcType=VARCHAR},
      sort = #{sort,jdbcType=INTEGER},
      watch_count = #{watchCount,jdbcType=INTEGER},
      on_sale = #{onSale,jdbcType=BOOLEAN},
      type_id = #{typeId,jdbcType=INTEGER},
      bought_users = #{boughtUsers,jdbcType=VARCHAR},
      bought_count = #{boughtCount,jdbcType=INTEGER},
      create_time = #{createTime,jdbcType=TIMESTAMP},
      update_time = #{updateTime,jdbcType=TIMESTAMP}
    where course_id = #{courseId,jdbcType=BIGINT}
  </update>
  <select id="ajaxCourseList" resultType="cn.lz.szp.pojo.vo.CourseVO">
    select <include refid="Base_Column_List"/> from course
    <where>
      <if test="title!=null and title!=''">
        and title=#{title}
      </if>
      <if test="subtitle!=null and subtitle!=''">
        and subtitle=#{subtitle}
      </if>
    </where>
    limit #{start},#{limit}
  </select>
  <select id="ajaxCourseListCount" resultType="java.lang.Integer">
    select count(*) from course
    <where>
      <if test="title!=null and title!=''">
        and title=#{title}
      </if>
      <if test="subtitle!=null and subtitle!=''">
        and subtitle=#{subtitle}
      </if>
    </where>
  </select>


  <select id="page" resultType="cn.lz.szp.pojo.entity.Course">
    select <include refid="Base_Column_List"/> from course
    <where>
      <if test="title!=null and title!=''">
        and title=#{title}
      </if>
      <if test="subtitle!=null and subtitle!=''">
        and subtitle=#{subtitle}
      </if>
    </where>
    limit #{start},#{limit}
  </select>

  <select id="countCourse" resultType="java.lang.Integer">
    select count(*) from course
    <where>
      <if test="title!=null and title!=''">
        and title=#{title}
      </if>
      <if test="subtitle!=null and subtitle!=''">
        and subtitle=#{subtitle}
      </if>
    </where>
  </select>

</mapper>